{"dependencies":[{"name":"./src/main.js","dynamic":true}],"generated":{"html":"<!DOCTYPE html>\n<html lang=\"en\">\n  <head>\n    <meta charset=\"utf-8\">\n    <title>parcel-test</title>\n  </head>\n  <body>\n    <div id=\"app\"></div>\n\n    <!-- PARCEL -->\n    <script src=\"/c869975bc39a1b34343d3f0da22cb982.js\"></script>\n\n    <!-- WEBPACK\n    <script src=\"./build/build.js\"></script> -->\n\n    <!-- ROLLUP\n    <script src=\"https://unpkg.com/vue\"></script>\n    <script src=\"rllp/vue-rollup-example.umd.js\"></script> -->\n  </body>\n</html>\n"},"hash":"d377062459fead420230bcd1ad371da0","cacheData":{}}